hive_path/__init__.py
hive_path/hive_path.py
hive_path/py.typed
hive_path-0.1.0.dist-info/WHEEL
hive_path-0.1.0.dist-info/METADATA
hive_path-0.1.0.dist-info/RECORD
