Metadata-Version: 2.3
Name: hive-path
Version: 0.1.0
Summary: A simple package pathlib extension for paths with Hive-style partitioning.
Author: Ben
Author-email: Ben <ishmandoo@gmail.com>
Requires-Python: >=3.10
